pypdns/__init__.py
pypdns/api.py
pypdns/errors.py
pypdns/py.typed
pypdns-2.3.1.dist-info/METADATA
pypdns-2.3.1.dist-info/WHEEL
pypdns-2.3.1.dist-info/entry_points.txt
pypdns-2.3.1.dist-info/licenses/LICENSE
pypdns-2.3.1.dist-info/RECORD
