Metadata-Version: 2.4
Name: pypdns
Version: 2.3.1
Summary: Python API for PDNS.
License-Expression: GPL-3.0+
License-File: LICENSE
Author: Raphaël Vinot
Author-email: raphael.vinot@circl.lu
Requires-Python: >=3.10
Classifier: Development Status :: 5 - Production/Stable
Classifier: Environment :: Console
Classifier: Intended Audience :: Science/Research
Classifier: Intended Audience :: Telecommunications Industry
Classifier: Programming Language :: Python :: 3
Classifier: Programming Language :: Python :: 3.10
Classifier: Programming Language :: Python :: 3.11
Classifier: Programming Language :: Python :: 3.12
Classifier: Programming Language :: Python :: 3.13
Classifier: Programming Language :: Python :: 3.14
Classifier: Topic :: Internet
Classifier: Topic :: Security
Provides-Extra: docs
Requires-Dist: dnspython (>=2.8.0)
Requires-Dist: requests-cache (>=1.2.1)
Requires-Dist: sphinx (>=9.1.0) ; (python_version >= "3.12") and (extra == "docs")
Project-URL: Documentation, https://pypdns.readthedocs.io
Project-URL: Repository, https://github.com/CIRCL/PyPDNS
